deeprobust/__init__.py
deeprobust/graph/__init__.py
deeprobust/graph/black_box.py
deeprobust/graph/utils.py
deeprobust/graph/visualization.py
deeprobust/graph/data/__init__.py
deeprobust/graph/data/attacked_data.py
deeprobust/graph/data/dataset.py
deeprobust/graph/data/pyg_dataset.py
deeprobust/graph/data/utils.py
deeprobust/graph/defense/__init__.py
deeprobust/graph/defense/adv_training.py
deeprobust/graph/defense/chebnet.py
deeprobust/graph/defense/gat.py
deeprobust/graph/defense/gcn.py
deeprobust/graph/defense/gcn_preprocess.py
deeprobust/graph/defense/median_gcn.py
deeprobust/graph/defense/node_embedding.py
deeprobust/graph/defense/pgd.py
deeprobust/graph/defense/prognn.py
deeprobust/graph/defense/r_gcn.py
deeprobust/graph/defense/sgc.py
deeprobust/graph/defense/simpgcn.py
deeprobust/graph/defense_pyg/__init__.py
deeprobust/graph/defense_pyg/airgnn.py
deeprobust/graph/defense_pyg/appnp.py
deeprobust/graph/defense_pyg/base_model.py
deeprobust/graph/defense_pyg/gat.py
deeprobust/graph/defense_pyg/gcn.py
deeprobust/graph/defense_pyg/gpr.py
deeprobust/graph/defense_pyg/mygat_conv.py
deeprobust/graph/defense_pyg/sage.py
deeprobust/graph/global_attack/__init__.py
deeprobust/graph/global_attack/base_attack.py
deeprobust/graph/global_attack/dice.py
deeprobust/graph/global_attack/mettack.py
deeprobust/graph/global_attack/nipa.py
deeprobust/graph/global_attack/node_embedding_attack.py
deeprobust/graph/global_attack/prbcd.py
deeprobust/graph/global_attack/random_attack.py
deeprobust/graph/global_attack/topology_attack.py
deeprobust/graph/rl/__init__.py
deeprobust/graph/rl/env.py
deeprobust/graph/rl/nipa_config.py
deeprobust/graph/rl/nipa_env.py
deeprobust/graph/rl/nipa_nstep_replay_mem.py
deeprobust/graph/rl/nipa_q_net_node.py
deeprobust/graph/rl/nstep_replay_mem.py
deeprobust/graph/rl/q_net_node.py
deeprobust/graph/rl/rl_s2v_config.py
deeprobust/graph/rl/rl_s2v_env.py
deeprobust/graph/targeted_attack/__init__.py
deeprobust/graph/targeted_attack/base_attack.py
deeprobust-0.2.11.dist-info/LICENSE
deeprobust-0.2.11.dist-info/METADATA
deeprobust-0.2.11.dist-info/WHEEL
deeprobust-0.2.11.dist-info/top_level.txt
deeprobust-0.2.11.dist-info/RECORD
