Metadata-Version: 2.1
Name: deeprobust
Version: 0.2.11
Summary: A PyTorch library for adversarial robustness learning for image and graph data.
Home-page: https://github.com/DSE-MSU/DeepRobust
Author: MSU-DSE
Maintainer: MSU-DSE
License: MIT
Platform: UNKNOWN
Classifier: Intended Audience :: Developers
Classifier: Intended Audience :: Education
Classifier: Intended Audience :: Science/Research
Classifier: Programming Language :: Python :: 3.5
Classifier: Programming Language :: Python :: 3.6
Classifier: Programming Language :: Python :: 3.7
Classifier: Programming Language :: Python :: 3.8
Classifier: Topic :: Scientific/Engineering :: Mathematics
Classifier: Topic :: Software Development :: Libraries :: Python Modules
Classifier: Topic :: Software Development :: Libraries
License-File: LICENSE
Requires-Dist: matplotlib (>=3.1.1)
Requires-Dist: numpy (>=1.17.1)
Requires-Dist: torch (>=1.2.0)
Requires-Dist: scipy (>=1.3.1)
Requires-Dist: torchvision (>=0.4.0)
Requires-Dist: texttable (>=1.6.2)
Requires-Dist: networkx (>=2.4)
Requires-Dist: numba (>=0.48.0)
Requires-Dist: Pillow (>=7.0.0)
Requires-Dist: scikit-learn (>=0.22.1)
Requires-Dist: scikit-image (>=0.0)
Requires-Dist: tensorboardX (>=2.0)
Requires-Dist: tqdm (>=3.0)
Requires-Dist: gensim (>=4.3.0)
